{
  "openapi": "3.0.4",
  "info": {
    "title": "GymLinkPro",
    "version": "1.0"
  },
  "paths": {
    "/api/ClassRegistrations": {
      "get": {
        "tags": [
          "ClassRegistrations"
        ],
        "responses": {
          "200": {
            "description": "OK",
            "content": {
              "text/plain": {
                "schema": {
                  "type": "array",
                  "items": {
                    "$ref": "#/components/schemas/ClassRegistration"
                  }
                }
              },
              "application/json": {
                "schema": {
                  "type": "array",
                  "items": {
                    "$ref": "#/components/schemas/ClassRegistration"
                  }
                }
              },
              "text/json": {
                "schema": {
                  "type": "array",
                  "items": {
                    "$ref": "#/components/schemas/ClassRegistration"
                  }
                }
              }
            }
          }
        }
      },
      "post": {
        "tags": [
          "ClassRegistrations"
        ],
        "requestBody": {
          "content": {
            "application/json": {
              "schema": {
                "$ref": "#/components/schemas/ClassRegistration"
              }
            },
            "text/json": {
              "schema": {
                "$ref": "#/components/schemas/ClassRegistration"
              }
            },
            "application/*+json": {
              "schema": {
                "$ref": "#/components/schemas/ClassRegistration"
              }
            }
          }
        },
        "responses": {
          "200": {
            "description": "OK",
            "content": {
              "text/plain": {
                "schema": {
                  "$ref": "#/components/schemas/ClassRegistration"
                }
              },
              "application/json": {
                "schema": {
                  "$ref": "#/components/schemas/ClassRegistration"
                }
              },
              "text/json": {
                "schema": {
                  "$ref": "#/components/schemas/ClassRegistration"
                }
              }
            }
          }
        }
      }
    },
    "/api/ClassRegistrations/{id}": {
      "get": {
        "tags": [
          "ClassRegistrations"
        ],
        "parameters": [
          {
            "name": "id",
            "in": "path",
            "required": true,
            "schema": {
              "type": "integer",
              "format": "int32"
            }
          }
        ],
        "responses": {
          "200": {
            "description": "OK",
            "content": {
              "text/plain": {
                "schema": {
                  "$ref": "#/components/schemas/ClassRegistration"
                }
              },
              "application/json": {
                "schema": {
                  "$ref": "#/components/schemas/ClassRegistration"
                }
              },
              "text/json": {
                "schema": {
                  "$ref": "#/components/schemas/ClassRegistration"
                }
              }
            }
          }
        }
      },
      "put": {
        "tags": [
          "ClassRegistrations"
        ],
        "parameters": [
          {
            "name": "id",
            "in": "path",
            "required": true,
            "schema": {
              "type": "integer",
              "format": "int32"
            }
          }
        ],
        "requestBody": {
          "content": {
            "application/json": {
              "schema": {
                "$ref": "#/components/schemas/ClassRegistration"
              }
            },
            "text/json": {
              "schema": {
                "$ref": "#/components/schemas/ClassRegistration"
              }
            },
            "application/*+json": {
              "schema": {
                "$ref": "#/components/schemas/ClassRegistration"
              }
            }
          }
        },
        "responses": {
          "200": {
            "description": "OK"
          }
        }
      },
      "delete": {
        "tags": [
          "ClassRegistrations"
        ],
        "parameters": [
          {
            "name": "id",
            "in": "path",
            "required": true,
            "schema": {
              "type": "integer",
              "format": "int32"
            }
          }
        ],
        "responses": {
          "200": {
            "description": "OK"
          }
        }
      }
    },
    "/api/GymClasses": {
      "get": {
        "tags": [
          "GymClasses"
        ],
        "responses": {
          "200": {
            "description": "OK",
            "content": {
              "text/plain": {
                "schema": {
                  "type": "array",
                  "items": {
                    "$ref": "#/components/schemas/GymClass"
                  }
                }
              },
              "application/json": {
                "schema": {
                  "type": "array",
                  "items": {
                    "$ref": "#/components/schemas/GymClass"
                  }
                }
              },
              "text/json": {
                "schema": {
                  "type": "array",
                  "items": {
                    "$ref": "#/components/schemas/GymClass"
                  }
                }
              }
            }
          }
        }
      },
      "post": {
        "tags": [
          "GymClasses"
        ],
        "requestBody": {
          "content": {
            "application/json": {
              "schema": {
                "$ref": "#/components/schemas/GymClass"
              }
            },
            "text/json": {
              "schema": {
                "$ref": "#/components/schemas/GymClass"
              }
            },
            "application/*+json": {
              "schema": {
                "$ref": "#/components/schemas/GymClass"
              }
            }
          }
        },
        "responses": {
          "200": {
            "description": "OK",
            "content": {
              "text/plain": {
                "schema": {
                  "$ref": "#/components/schemas/GymClass"
                }
              },
              "application/json": {
                "schema": {
                  "$ref": "#/components/schemas/GymClass"
                }
              },
              "text/json": {
                "schema": {
                  "$ref": "#/components/schemas/GymClass"
                }
              }
            }
          }
        }
      }
    },
    "/api/GymClasses/{id}": {
      "get": {
        "tags": [
          "GymClasses"
        ],
        "parameters": [
          {
            "name": "id",
            "in": "path",
            "required": true,
            "schema": {
              "type": "integer",
              "format": "int32"
            }
          }
        ],
        "responses": {
          "200": {
            "description": "OK",
            "content": {
              "text/plain": {
                "schema": {
                  "$ref": "#/components/schemas/GymClass"
                }
              },
              "application/json": {
                "schema": {
                  "$ref": "#/components/schemas/GymClass"
                }
              },
              "text/json": {
                "schema": {
                  "$ref": "#/components/schemas/GymClass"
                }
              }
            }
          }
        }
      },
      "put": {
        "tags": [
          "GymClasses"
        ],
        "parameters": [
          {
            "name": "id",
            "in": "path",
            "required": true,
            "schema": {
              "type": "integer",
              "format": "int32"
            }
          }
        ],
        "requestBody": {
          "content": {
            "application/json": {
              "schema": {
                "$ref": "#/components/schemas/GymClass"
              }
            },
            "text/json": {
              "schema": {
                "$ref": "#/components/schemas/GymClass"
              }
            },
            "application/*+json": {
              "schema": {
                "$ref": "#/components/schemas/GymClass"
              }
            }
          }
        },
        "responses": {
          "200": {
            "description": "OK"
          }
        }
      },
      "delete": {
        "tags": [
          "GymClasses"
        ],
        "parameters": [
          {
            "name": "id",
            "in": "path",
            "required": true,
            "schema": {
              "type": "integer",
              "format": "int32"
            }
          }
        ],
        "responses": {
          "200": {
            "description": "OK"
          }
        }
      }
    },
    "/api/ProjectLinks": {
      "get": {
        "tags": [
          "ProjectLinks"
        ],
        "responses": {
          "200": {
            "description": "OK",
            "content": {
              "text/plain": {
                "schema": {
                  "type": "array",
                  "items": {
                    "$ref": "#/components/schemas/ProjectLink"
                  }
                }
              },
              "application/json": {
                "schema": {
                  "type": "array",
                  "items": {
                    "$ref": "#/components/schemas/ProjectLink"
                  }
                }
              },
              "text/json": {
                "schema": {
                  "type": "array",
                  "items": {
                    "$ref": "#/components/schemas/ProjectLink"
                  }
                }
              }
            }
          }
        }
      },
      "post": {
        "tags": [
          "ProjectLinks"
        ],
        "requestBody": {
          "content": {
            "application/json": {
              "schema": {
                "$ref": "#/components/schemas/ProjectLink"
              }
            },
            "text/json": {
              "schema": {
                "$ref": "#/components/schemas/ProjectLink"
              }
            },
            "application/*+json": {
              "schema": {
                "$ref": "#/components/schemas/ProjectLink"
              }
            }
          }
        },
        "responses": {
          "200": {
            "description": "OK",
            "content": {
              "text/plain": {
                "schema": {
                  "$ref": "#/components/schemas/ProjectLink"
                }
              },
              "application/json": {
                "schema": {
                  "$ref": "#/components/schemas/ProjectLink"
                }
              },
              "text/json": {
                "schema": {
                  "$ref": "#/components/schemas/ProjectLink"
                }
              }
            }
          }
        }
      }
    },
    "/api/ProjectLinks/{id}": {
      "get": {
        "tags": [
          "ProjectLinks"
        ],
        "parameters": [
          {
            "name": "id",
            "in": "path",
            "required": true,
            "schema": {
              "type": "integer",
              "format": "int32"
            }
          }
        ],
        "responses": {
          "200": {
            "description": "OK",
            "content": {
              "text/plain": {
                "schema": {
                  "$ref": "#/components/schemas/ProjectLink"
                }
              },
              "application/json": {
                "schema": {
                  "$ref": "#/components/schemas/ProjectLink"
                }
              },
              "text/json": {
                "schema": {
                  "$ref": "#/components/schemas/ProjectLink"
                }
              }
            }
          }
        }
      },
      "put": {
        "tags": [
          "ProjectLinks"
        ],
        "parameters": [
          {
            "name": "id",
            "in": "path",
            "required": true,
            "schema": {
              "type": "integer",
              "format": "int32"
            }
          }
        ],
        "requestBody": {
          "content": {
            "application/json": {
              "schema": {
                "$ref": "#/components/schemas/ProjectLink"
              }
            },
            "text/json": {
              "schema": {
                "$ref": "#/components/schemas/ProjectLink"
              }
            },
            "application/*+json": {
              "schema": {
                "$ref": "#/components/schemas/ProjectLink"
              }
            }
          }
        },
        "responses": {
          "200": {
            "description": "OK"
          }
        }
      },
      "delete": {
        "tags": [
          "ProjectLinks"
        ],
        "parameters": [
          {
            "name": "id",
            "in": "path",
            "required": true,
            "schema": {
              "type": "integer",
              "format": "int32"
            }
          }
        ],
        "responses": {
          "200": {
            "description": "OK"
          }
        }
      }
    },
    "/api/ProjectMembers": {
      "get": {
        "tags": [
          "ProjectMembers"
        ],
        "responses": {
          "200": {
            "description": "OK",
            "content": {
              "text/plain": {
                "schema": {
                  "type": "array",
                  "items": {
                    "$ref": "#/components/schemas/ProjectMember"
                  }
                }
              },
              "application/json": {
                "schema": {
                  "type": "array",
                  "items": {
                    "$ref": "#/components/schemas/ProjectMember"
                  }
                }
              },
              "text/json": {
                "schema": {
                  "type": "array",
                  "items": {
                    "$ref": "#/components/schemas/ProjectMember"
                  }
                }
              }
            }
          }
        }
      },
      "post": {
        "tags": [
          "ProjectMembers"
        ],
        "requestBody": {
          "content": {
            "application/json": {
              "schema": {
                "$ref": "#/components/schemas/ProjectMember"
              }
            },
            "text/json": {
              "schema": {
                "$ref": "#/components/schemas/ProjectMember"
              }
            },
            "application/*+json": {
              "schema": {
                "$ref": "#/components/schemas/ProjectMember"
              }
            }
          }
        },
        "responses": {
          "200": {
            "description": "OK",
            "content": {
              "text/plain": {
                "schema": {
                  "$ref": "#/components/schemas/ProjectMember"
                }
              },
              "application/json": {
                "schema": {
                  "$ref": "#/components/schemas/ProjectMember"
                }
              },
              "text/json": {
                "schema": {
                  "$ref": "#/components/schemas/ProjectMember"
                }
              }
            }
          }
        }
      }
    },
    "/api/ProjectMembers/{id}": {
      "get": {
        "tags": [
          "ProjectMembers"
        ],
        "parameters": [
          {
            "name": "id",
            "in": "path",
            "required": true,
            "schema": {
              "type": "integer",
              "format": "int32"
            }
          }
        ],
        "responses": {
          "200": {
            "description": "OK",
            "content": {
              "text/plain": {
                "schema": {
                  "$ref": "#/components/schemas/ProjectMember"
                }
              },
              "application/json": {
                "schema": {
                  "$ref": "#/components/schemas/ProjectMember"
                }
              },
              "text/json": {
                "schema": {
                  "$ref": "#/components/schemas/ProjectMember"
                }
              }
            }
          }
        }
      },
      "put": {
        "tags": [
          "ProjectMembers"
        ],
        "parameters": [
          {
            "name": "id",
            "in": "path",
            "required": true,
            "schema": {
              "type": "integer",
              "format": "int32"
            }
          }
        ],
        "requestBody": {
          "content": {
            "application/json": {
              "schema": {
                "$ref": "#/components/schemas/ProjectMember"
              }
            },
            "text/json": {
              "schema": {
                "$ref": "#/components/schemas/ProjectMember"
              }
            },
            "application/*+json": {
              "schema": {
                "$ref": "#/components/schemas/ProjectMember"
              }
            }
          }
        },
        "responses": {
          "200": {
            "description": "OK"
          }
        }
      },
      "delete": {
        "tags": [
          "ProjectMembers"
        ],
        "parameters": [
          {
            "name": "id",
            "in": "path",
            "required": true,
            "schema": {
              "type": "integer",
              "format": "int32"
            }
          }
        ],
        "responses": {
          "200": {
            "description": "OK"
          }
        }
      }
    },
    "/api/Projects": {
      "get": {
        "tags": [
          "Projects"
        ],
        "responses": {
          "200": {
            "description": "OK",
            "content": {
              "text/plain": {
                "schema": {
                  "type": "array",
                  "items": {
                    "$ref": "#/components/schemas/Project"
                  }
                }
              },
              "application/json": {
                "schema": {
                  "type": "array",
                  "items": {
                    "$ref": "#/components/schemas/Project"
                  }
                }
              },
              "text/json": {
                "schema": {
                  "type": "array",
                  "items": {
                    "$ref": "#/components/schemas/Project"
                  }
                }
              }
            }
          }
        }
      },
      "post": {
        "tags": [
          "Projects"
        ],
        "requestBody": {
          "content": {
            "application/json": {
              "schema": {
                "$ref": "#/components/schemas/Project"
              }
            },
            "text/json": {
              "schema": {
                "$ref": "#/components/schemas/Project"
              }
            },
            "application/*+json": {
              "schema": {
                "$ref": "#/components/schemas/Project"
              }
            }
          }
        },
        "responses": {
          "200": {
            "description": "OK",
            "content": {
              "text/plain": {
                "schema": {
                  "$ref": "#/components/schemas/Project"
                }
              },
              "application/json": {
                "schema": {
                  "$ref": "#/components/schemas/Project"
                }
              },
              "text/json": {
                "schema": {
                  "$ref": "#/components/schemas/Project"
                }
              }
            }
          }
        }
      }
    },
    "/api/Projects/{id}": {
      "get": {
        "tags": [
          "Projects"
        ],
        "parameters": [
          {
            "name": "id",
            "in": "path",
            "required": true,
            "schema": {
              "type": "integer",
              "format": "int32"
            }
          }
        ],
        "responses": {
          "200": {
            "description": "OK",
            "content": {
              "text/plain": {
                "schema": {
                  "$ref": "#/components/schemas/Project"
                }
              },
              "application/json": {
                "schema": {
                  "$ref": "#/components/schemas/Project"
                }
              },
              "text/json": {
                "schema": {
                  "$ref": "#/components/schemas/Project"
                }
              }
            }
          }
        }
      },
      "put": {
        "tags": [
          "Projects"
        ],
        "parameters": [
          {
            "name": "id",
            "in": "path",
            "required": true,
            "schema": {
              "type": "integer",
              "format": "int32"
            }
          }
        ],
        "requestBody": {
          "content": {
            "application/json": {
              "schema": {
                "$ref": "#/components/schemas/Project"
              }
            },
            "text/json": {
              "schema": {
                "$ref": "#/components/schemas/Project"
              }
            },
            "application/*+json": {
              "schema": {
                "$ref": "#/components/schemas/Project"
              }
            }
          }
        },
        "responses": {
          "200": {
            "description": "OK"
          }
        }
      },
      "delete": {
        "tags": [
          "Projects"
        ],
        "parameters": [
          {
            "name": "id",
            "in": "path",
            "required": true,
            "schema": {
              "type": "integer",
              "format": "int32"
            }
          }
        ],
        "responses": {
          "200": {
            "description": "OK"
          }
        }
      }
    },
    "/api/Users": {
      "get": {
        "tags": [
          "Users"
        ],
        "responses": {
          "200": {
            "description": "OK",
            "content": {
              "text/plain": {
                "schema": {
                  "type": "array",
                  "items": {
                    "$ref": "#/components/schemas/User"
                  }
                }
              },
              "application/json": {
                "schema": {
                  "type": "array",
                  "items": {
                    "$ref": "#/components/schemas/User"
                  }
                }
              },
              "text/json": {
                "schema": {
                  "type": "array",
                  "items": {
                    "$ref": "#/components/schemas/User"
                  }
                }
              }
            }
          }
        }
      },
      "post": {
        "tags": [
          "Users"
        ],
        "requestBody": {
          "content": {
            "application/json": {
              "schema": {
                "$ref": "#/components/schemas/User"
              }
            },
            "text/json": {
              "schema": {
                "$ref": "#/components/schemas/User"
              }
            },
            "application/*+json": {
              "schema": {
                "$ref": "#/components/schemas/User"
              }
            }
          }
        },
        "responses": {
          "200": {
            "description": "OK",
            "content": {
              "text/plain": {
                "schema": {
                  "$ref": "#/components/schemas/User"
                }
              },
              "application/json": {
                "schema": {
                  "$ref": "#/components/schemas/User"
                }
              },
              "text/json": {
                "schema": {
                  "$ref": "#/components/schemas/User"
                }
              }
            }
          }
        }
      }
    },
    "/api/Users/{id}": {
      "get": {
        "tags": [
          "Users"
        ],
        "parameters": [
          {
            "name": "id",
            "in": "path",
            "required": true,
            "schema": {
              "type": "integer",
              "format": "int32"
            }
          }
        ],
        "responses": {
          "200": {
            "description": "OK",
            "content": {
              "text/plain": {
                "schema": {
                  "$ref": "#/components/schemas/User"
                }
              },
              "application/json": {
                "schema": {
                  "$ref": "#/components/schemas/User"
                }
              },
              "text/json": {
                "schema": {
                  "$ref": "#/components/schemas/User"
                }
              }
            }
          }
        }
      },
      "put": {
        "tags": [
          "Users"
        ],
        "parameters": [
          {
            "name": "id",
            "in": "path",
            "required": true,
            "schema": {
              "type": "integer",
              "format": "int32"
            }
          }
        ],
        "requestBody": {
          "content": {
            "application/json": {
              "schema": {
                "$ref": "#/components/schemas/User"
              }
            },
            "text/json": {
              "schema": {
                "$ref": "#/components/schemas/User"
              }
            },
            "application/*+json": {
              "schema": {
                "$ref": "#/components/schemas/User"
              }
            }
          }
        },
        "responses": {
          "200": {
            "description": "OK"
          }
        }
      },
      "delete": {
        "tags": [
          "Users"
        ],
        "parameters": [
          {
            "name": "id",
            "in": "path",
            "required": true,
            "schema": {
              "type": "integer",
              "format": "int32"
            }
          }
        ],
        "responses": {
          "200": {
            "description": "OK"
          }
        }
      }
    }
  },
  "components": {
    "schemas": {
      "ClassRegistration": {
        "type": "object",
        "properties": {
          "classRegistrationId": {
            "type": "integer",
            "format": "int32"
          },
          "memberId": {
            "type": "integer",
            "format": "int32"
          },
          "classId": {
            "type": "integer",
            "format": "int32"
          },
          "status": {
            "type": "string",
            "nullable": true
          },
          "registrationDate": {
            "type": "string",
            "format": "date-time"
          }
        },
        "additionalProperties": false
      },
      "GymClass": {
        "type": "object",
        "properties": {
          "gymClassId": {
            "type": "integer",
            "format": "int32"
          },
          "name": {
            "type": "string",
            "nullable": true
          },
          "trainerId": {
            "type": "integer",
            "format": "int32"
          },
          "scheduleTime": {
            "type": "string",
            "format": "date-time"
          },
          "maxCapacity": {
            "type": "integer",
            "format": "int32"
          }
        },
        "additionalProperties": false
      },
      "Project": {
        "type": "object",
        "properties": {
          "projectId": {
            "type": "integer",
            "format": "int32"
          },
          "creatorId": {
            "type": "integer",
            "format": "int32"
          },
          "name": {
            "type": "string",
            "nullable": true
          },
          "description": {
            "type": "string",
            "nullable": true
          }
        },
        "additionalProperties": false
      },
      "ProjectLink": {
        "type": "object",
        "properties": {
          "projectLinkId": {
            "type": "integer",
            "format": "int32"
          },
          "projectId": {
            "type": "integer",
            "format": "int32"
          },
          "url": {
            "type": "string",
            "nullable": true
          },
          "description": {
            "type": "string",
            "nullable": true
          },
          "addedByUserId": {
            "type": "integer",
            "format": "int32"
          },
          "category": {
            "type": "string",
            "nullable": true
          }
        },
        "additionalProperties": false
      },
      "ProjectMember": {
        "type": "object",
        "properties": {
          "projectMemberId": {
            "type": "integer",
            "format": "int32"
          },
          "memberId": {
            "type": "integer",
            "format": "int32"
          },
          "projectId": {
            "type": "integer",
            "format": "int32"
          },
          "role": {
            "type": "string",
            "nullable": true
          }
        },
        "additionalProperties": false
      },
      "User": {
        "type": "object",
        "properties": {
          "userId": {
            "type": "integer",
            "format": "int32"
          },
          "firstName": {
            "type": "string",
            "nullable": true
          },
          "lastName": {
            "type": "string",
            "nullable": true
          },
          "email": {
            "type": "string",
            "nullable": true
          },
          "phoneNumber": {
            "type": "string",
            "nullable": true
          },
          "role": {
            "type": "string",
            "nullable": true
          }
        },
        "additionalProperties": false
      }
    }
  }
}